solldex_api/__init__.py
solldex_api/solldex_api.py
solldex_api/solldex_models.py
solldex_api_client-0.1.18.dist-info/LICENSE
solldex_api_client-0.1.18.dist-info/METADATA
solldex_api_client-0.1.18.dist-info/WHEEL
solldex_api_client-0.1.18.dist-info/top_level.txt
solldex_api_client-0.1.18.dist-info/RECORD
